{"data":{"Id":0,"Userid":0,"Title":"","DeviceTitle":"AAGS023","BarCode":"8039","CateId":13,"FactoryId":149,"SellerId":0,"ClassicId":[{"Id":141,"Name":"\u4e0a\u97629\u4e2a\u4e0b\u97626\u4e2a","Groups":[{"Id":78,"Name":"mod1","Special":0,"Buttons":[{"Id":1,"Name":"Mode1","Image":"https://zlmicro.oss-cn-shenzhen.aliyuncs.com/images/gif/OverseasMSfrequency_01.gif","ImageClick":"","Command":31,"StopCommand":"30"},{"Id":2,"Name":"Mode2","Image":"https://zlmicro.oss-cn-shenzhen.aliyuncs.com/images/gif/OverseasMSfrequency_02.gif","ImageClick":"","Command":32,"StopCommand":"30"},{"Id":3,"Name":"Mode3","Image":"https://zlmicro.oss-cn-shenzhen.aliyuncs.com/images/gif/OverseasMSfrequency_03.gif","ImageClick":"","Command":33,"StopCommand":"30"},{"Id":4,"Name":"Mode4","Image":"https://zlmicro.oss-cn-shenzhen.aliyuncs.com/images/gif/OverseasMSfrequency_04.gif","ImageClick":"","Command":34,"StopCommand":"30"},{"Id":5,"Name":"Mode5","Image":"https://zlmicro.oss-cn-shenzhen.aliyuncs.com/images/gif/OverseasMSfrequency_05.gif","ImageClick":"","Command":35,"StopCommand":"30"},{"Id":6,"Name":"Mode6","Image":"https://zlmicro.oss-cn-shenzhen.aliyuncs.com/images/gif/OverseasMSfrequency_06.gif","ImageClick":"","Command":36,"StopCommand":"30"},{"Id":7,"Name":"Mode7","Image":"https://zlmicro.oss-cn-shenzhen.aliyuncs.com/images/gif/OverseasMSfrequency_07.gif","ImageClick":"","Command":37,"StopCommand":"30"},{"Id":8,"Name":"Mode8","Image":"https://zlmicro.oss-cn-shenzhen.aliyuncs.com/images/gif/OverseasMSfrequency_08.gif","ImageClick":"","Command":38,"StopCommand":"30"},{"Id":9,"Name":"Mode9","Image":"https://zlmicro.oss-cn-shenzhen.aliyuncs.com/images/gif/OverseasMSfrequency_09.gif","ImageClick":"","Command":39,"StopCommand":"30"}]},{"Id":79,"Name":"mod2","Special":0,"Buttons":[{"Id":19,"Name":"Mode1","Image":"https://zlmicro.oss-cn-shenzhen.aliyuncs.com/images/gif/OverseasMSfrequency_01.gif","ImageClick":"","Command":41,"StopCommand":"40"},{"Id":20,"Name":"Mode2","Image":"https://zlmicro.oss-cn-shenzhen.aliyuncs.com/images/gif/OverseasMSfrequency_02.gif","ImageClick":"","Command":42,"StopCommand":"40"},{"Id":21,"Name":"Mode3","Image":"https://zlmicro.oss-cn-shenzhen.aliyuncs.com/images/gif/OverseasMSfrequency_03.gif","ImageClick":"","Command":43,"StopCommand":"40"},{"Id":22,"Name":"Mode4","Image":"https://zlmicro.oss-cn-shenzhen.aliyuncs.com/images/gif/OverseasMSfrequency_04.gif","ImageClick":"","Command":44,"StopCommand":"40"},{"Id":23,"Name":"Mode5","Image":"https://zlmicro.oss-cn-shenzhen.aliyuncs.com/images/gif/OverseasMSfrequency_05.gif","ImageClick":"","Command":45,"StopCommand":"40"},{"Id":24,"Name":"Mode6","Image":"https://zlmicro.oss-cn-shenzhen.aliyuncs.com/images/gif/OverseasMSfrequency_06.gif","ImageClick":"","Command":46,"StopCommand":"40"}]}]}],"Setting":null,"Wireless":"2.4g","CreateTime":1678175040,"UpdateTime":1682565303,"Status":1,"Pics":"https://static.zlmicro.com/images/product/20230307/20230307154359518.png","Func":"{\"kegel\":false,\"classic\":true,\"music\":true,\"shake\":true,\"intera\":true,\"heating\":false,\"finger\":true,\"discharge\":false,\"voice\":false,\"ai_voice\":false,\"trends\":false,\"video\":true,\"game\":true,\"video_voice\":false,\"strike\":false,\"switch_voice\":false,\"tot\":false}","FuncObj":{"kegel":false,"classic":true,"music":true,"shake":true,"intera":true,"heating":false,"finger":true},"ProductFuncs":[{"Id":2,"Name":"\u7ecf\u5178\u6a21\u5f0f","Code":"classic"},{"Id":3,"Name":"\u97f3\u4e50\u6a21\u5f0f","Code":"music"},{"Id":4,"Name":"\u6447\u4e00\u6447","Code":"shake"},{"Id":5,"Name":"\u4e92\u52a8\u6a21\u5f0f","Code":"intera"},{"Id":7,"Name":"\u5212\u4e00\u5212","Code":"finger"},{"Id":12,"Name":"\u89c6\u9891\u6a21\u5f0f","Code":"video"},{"Id":13,"Name":"\u6e38\u620f\u6a21\u5f0f","Code":"game"}],"BroadcastPrefix":"77 62 4d 53 45","BleName":"","IsBlacklist":0,"Qrcode":"https://static.zlmicro.com/images/product/qrcode/8039.png","GamePath":""},"response":{"result":true,"errorCode":10000,"msg":"Success"}}